  {
      "title": "Ingest Rate By Station Over Time",
      "visState": "{\"aggs\":[{\"enabled\":true,\"id\":\"1\",\"params\":{\"customLabel\":\"Rate/sec\",\"field\":\"ingest_rate\"},\"schema\":\"metric\",\"type\":\"avg\"},{\"enabled\":true,\"id\":\"2\",\"params\":{\"customInterval\":\"2h\",\"extended_bounds\":{},\"field\":\"updated_at\",\"interval\":\"auto\",\"min_doc_count\":1},\"schema\":\"segment\",\"type\":\"date_histogram\"},{\"enabled\":true,\"id\":\"3\",\"params\":{\"field\":\"ingest_station\",\"order\":\"desc\",\"orderBy\":\"1\",\"size\":5},\"schema\":\"group\",\"type\":\"terms\"}],\"listeners\":{},\"params\":{\"addLegend\":true,\"addTimeMarker\":false,\"addTooltip\":true,\"categoryAxes\":[{\"id\":\"CategoryAxis-1\",\"labels\":{\"show\":true,\"truncate\":100},\"position\":\"bottom\",\"scale\":{\"type\":\"linear\"},\"show\":true,\"style\":{},\"title\":{\"text\":\"updated_at per 30 seconds\"},\"type\":\"category\"}],\"grid\":{\"categoryLines\":false,\"style\":{\"color\":\"#eee\"}},\"legendPosition\":\"right\",\"seriesParams\":[{\"data\":{\"id\":\"1\",\"label\":\"Rate/sec\"},\"drawLinesBetweenPoints\":true,\"mode\":\"normal\",\"show\":\"true\",\"showCircles\":true,\"type\":\"line\",\"valueAxis\":\"ValueAxis-1\"}],\"times\":[],\"type\":\"line\",\"valueAxes\":[{\"id\":\"ValueAxis-1\",\"labels\":{\"filter\":false,\"rotate\":0,\"show\":true,\"truncate\":100},\"name\":\"LeftAxis-1\",\"position\":\"left\",\"scale\":{\"mode\":\"normal\",\"type\":\"linear\"},\"show\":true,\"style\":{},\"title\":{\"text\":\"Rate/sec\"},\"type\":\"value\"}]},\"title\":\"Ingest Rate By Station\",\"type\":\"line\"}",
      "uiStateJSON": "{}",
      "description": "",
      "version": 1,
      "kibanaSavedObjectMeta": {
        "searchSourceJSON": "{\"index\":\"dms-z1-raw-v1\",\"query\":{\"match_all\":{}},\"filter\":[]}"
      }
  }
